CHANGES.txt
README.txt
setup.cfg
setup.py
src/repoze/__init__.py
src/repoze.bfg.httprequest.egg-info/PKG-INFO
src/repoze.bfg.httprequest.egg-info/SOURCES.txt
src/repoze.bfg.httprequest.egg-info/dependency_links.txt
src/repoze.bfg.httprequest.egg-info/namespace_packages.txt
src/repoze.bfg.httprequest.egg-info/not-zip-safe
src/repoze.bfg.httprequest.egg-info/requires.txt
src/repoze.bfg.httprequest.egg-info/top_level.txt
src/repoze/bfg/__init__.py
src/repoze/bfg/httprequest/README.txt
src/repoze/bfg/httprequest/__init__.py
src/repoze/bfg/httprequest/adapter.py
src/repoze/bfg/httprequest/configure.zcml
src/repoze/bfg/httprequest/tests/__init__.py
src/repoze/bfg/httprequest/tests/test_doctests.py