Metadata-Version: 1.0
Name: repoze.bfg.httprequest
Version: 0.3
Summary: Adaptable request interfaces.
Home-page: http://pypi.python.org/pypi/repoze.bfg.httprequest
Author: Malthe Borch and Stefan Eletzhofer
Author-email: repoze-dev@lists.repoze.org
License: ZPL 2.1
Keywords: zope3 repoze bfg
Platform: UNKNOWN
Classifier: Development Status :: 4 - Beta
Classifier: Environment :: Web Environment
Classifier: Intended Audience :: Developers
Classifier: License :: OSI Approved :: Zope Public License
Classifier: Programming Language :: Python
Classifier: Natural Language :: English
Classifier: Operating System :: OS Independent
Classifier: Topic :: Internet :: WWW/HTTP
Classifier: Framework :: Zope3
